izihawa_loglib/__init__.py
izihawa_loglib/formatters.py
izihawa_loglib/handlers.py
izihawa_loglib/request_context.py
izihawa_loglib-1.1.21.dist-info/METADATA
izihawa_loglib-1.1.21.dist-info/WHEEL
izihawa_loglib-1.1.21.dist-info/RECORD
