Metadata-Version: 2.1
Name: izihawa_loglib
Version: 1.1.21
Summary: Izihawa log utilities
Author: Pasha Podolsky
Author-email: ppodolsky@me.com
Requires-Python: >=3.8.1,<4.0.0
Classifier: Programming Language :: Python :: 3
Classifier: Programming Language :: Python :: 3.9
Classifier: Programming Language :: Python :: 3.10
Classifier: Programming Language :: Python :: 3.11
Classifier: Programming Language :: Python :: 3.12
Requires-Dist: confuse (>=2.0.1,<3.0.0)
Requires-Dist: izihawa-types (>=0.1.4,<0.2.0)
Requires-Dist: izihawa-utils (>=1.2.2,<2.0.0)
Requires-Dist: orjson (>=3.9.10,<4.0.0)
